setup.py
gaussian_binomial_prob/Binomialdistribution.py
gaussian_binomial_prob/Gaussiandistribution.py
gaussian_binomial_prob/Generaldistribution.py
gaussian_binomial_prob/__init__.py
gaussian_binomial_prob.egg-info/PKG-INFO
gaussian_binomial_prob.egg-info/SOURCES.txt
gaussian_binomial_prob.egg-info/dependency_links.txt
gaussian_binomial_prob.egg-info/not-zip-safe
gaussian_binomial_prob.egg-info/top_level.txt